{"Train F1 normal": 0.12012012302875519, "Val F1 normal": 0.0, "_timestamp": 1722716262.082533, "Train F1 AVNRT": 33.57142639160156, "Val F1 AVNRT": 28.571430206298828, "Train F1 AVRT": 16.06060791015625, "Val F1 AVRT": 20.0, "Train F1 concealed": 35.748138427734375, "Val F1 concealed": 30.76923179626465, "Train F1 EAT": 10.66573715209961, "Val F1 EAT": 5.128204822540283, "Best val F1": 16.893772780895233, "Weight Name": "ECGCNNClassifier_fold1_tachy_B64_L2e-07_03-08-24-22-16", "Best Val F1 normal": 0.0, "Best Val F1 AVNRT": 28.571430206298828, "Best Val F1 AVRT": 20.0, "Best Val F1 concealed": 30.76923179626465, "Best Val F1 EAT": 5.128204822540283, "Training Confusion Matrix": {"_type": "table-file", "sha256": "3888e888d17dd034714ef0f0285662850676156aa2dca0dff945f51485e913e6", "size": 364, "artifact_path": "wandb-client-artifact://gvymjppl10xk5f6uz3im5bbfcs9wbl02ue9l7559ijrq3jt5npaz3bju1ygr72ft9tdu8leq14536xpx4lurikb7f4hr60s4whax4wtj0mboaz0zky8h9a9y2ozakn02/Training Confusion Matrix.table.json", "_latest_artifact_path": "wandb-client-artifact://1sjqeb9y6xb4ue7b1wyqieik74l43t2nk91uqs14jcjyrya2dc0kipk8fku0kybqekkyw6m05hm0fa1n42n2gfyk8udxz316jpxam02p0tx3up37b44a0s8jj72sc1hy:latest/Training Confusion Matrix.table.json", "path": "media/table/Training Confusion Matrix_4_3888e888d17dd034714e.table.json", "ncols": 6, "nrows": 5}, "Training Confusion Matrix Heatmap": {"_type": "image-file", "sha256": "2ee2c718411cb36a3d204851876be2026ce1d9ac9d8cad865d5c923587007531", "size": 71818, "path": "media/images/Training Confusion Matrix Heatmap_4_2ee2c718411cb36a3d20.png", "format": "png", "width": 1000, "height": 1000}, "Validation Confusion Matrix": {"_type": "table-file", "sha256": "5546cd5ccc72948784ffe2cbadbab59376be684a9543ba0dbcf05ac8f764a8cd", "size": 329, "artifact_path": "wandb-client-artifact://8zv7ntsurv97dluxea17sc6g3lrehpaph5sj9wr38nodklakdwticlged9yxw5ytn85t20s0ge5lgss4e9y8fu5z1gju63ay8ehqw5iiavecok5e4lkbl1hew0gqqg0g/Validation Confusion Matrix.table.json", "_latest_artifact_path": "wandb-client-artifact://oyp1k96ykheejw2dfmhrya10uik7dpwk02dz8vnhznukh6t739pi546pqc7y3lrv62p27i9xhaua4kvneucxanzzjqn0uh6mlpc6dmjfpqbw75z8cfuyf4qe2m506lb9:latest/Validation Confusion Matrix.table.json", "path": "media/table/Validation Confusion Matrix_4_5546cd5ccc72948784ff.table.json", "ncols": 6, "nrows": 5}, "Validation Confusion Matrix Heatmap": {"_type": "image-file", "sha256": "bc5435d711c7a93f366e2ac63b574924b671044fd661e89854a717f3079d3e54", "size": 65403, "path": "media/images/Validation Confusion Matrix Heatmap_4_bc5435d711c7a93f366e.png", "format": "png", "width": 1000, "height": 1000}, "train acc": 17.881642733010153, "train loss": 1.9654868694518688, "train vis loss": 1.4108385053039243, "train F1": 19.233205914497375, "val acc": 14.814814814814813, "val loss": 1.4520909415912926, "val F1": 16.893772780895233, "_runtime": 84.4079577922821, "_step": 4, "_wandb": {"runtime": 94}}