{"Train F1 normal": 99.82752227783203, "Val F1 normal": 96.875, "_timestamp": 1713381658.1116498, "Train F1 AVNRT": 99.76323699951172, "Val F1 AVNRT": 73.52941131591797, "Train F1 AVRT": 100.0, "Val F1 AVRT": 0.0, "Train F1 concealed": 99.98660278320312, "Val F1 concealed": 0.0, "Train F1 EAT": 99.99083709716797, "Val F1 EAT": 0.0, "Best val F1": 54.033225774765015, "Weight Name": "ECGCNNClassifier_fold2_tachy_B64_L1e-05_17-04-24-21-01", "Best Val F1 normal": 93.02326202392578, "Best Val F1 AVNRT": 70.0, "Best Val F1 AVRT": 57.142852783203125, "Best Val F1 concealed": 0.0, "Best Val F1 EAT": 50.0, "Training Confusion Matrix": {"_type": "table-file", "sha256": "aca40da0e84b831ce851eeef72b4604bad547716f77d7398b12dc701d016c284", "size": 356, "artifact_path": "wandb-client-artifact://ojrw3lojdf848c397gum003e5uh62r0ky1hmj0qouk1a0sqwxiea7wlh4avuzmjzcggzfzi5w0zl5nfzldb5lo2dpiwzryfmfp2srebcrspoh3awv6bw4ce8nhmhhwsb:latest/Training Confusion Matrix.table.json", "_latest_artifact_path": "wandb-client-artifact://ojrw3lojdf848c397gum003e5uh62r0ky1hmj0qouk1a0sqwxiea7wlh4avuzmjzcggzfzi5w0zl5nfzldb5lo2dpiwzryfmfp2srebcrspoh3awv6bw4ce8nhmhhwsb:latest/Training Confusion Matrix.table.json", "path": "media/table/Training Confusion Matrix_6_aca40da0e84b831ce851.table.json", "ncols": 6, "nrows": 5}, "Training Confusion Matrix Heatmap": {"_type": "image-file", "sha256": "cd643ad5f86670d7f696dbecaff3274ed6eb63cc9021edc2e6d768ab57b6a9ac", "size": 70021, "path": "media/images/Training Confusion Matrix Heatmap_6_cd643ad5f86670d7f696.png", "format": "png", "width": 1000, "height": 1000}, "Validation Confusion Matrix": {"_type": "table-file", "sha256": "d58a1958fb5f896daa5df3c244409d098930167dfec02bc100d1c7187b3778a6", "size": 328, "artifact_path": "wandb-client-artifact://dp6ejrg87qvaym5iepm9ed1ukas99fy0myvax82qwliccw0m598osvlwrknvp2dvqw9jkn5ldhop6oatkqw6vddxrf3sattkoav655kmrbhn7akb5rqmlpyvkuek2fur:latest/Validation Confusion Matrix.table.json", "_latest_artifact_path": "wandb-client-artifact://dp6ejrg87qvaym5iepm9ed1ukas99fy0myvax82qwliccw0m598osvlwrknvp2dvqw9jkn5ldhop6oatkqw6vddxrf3sattkoav655kmrbhn7akb5rqmlpyvkuek2fur:latest/Validation Confusion Matrix.table.json", "path": "media/table/Validation Confusion Matrix_6_d58a1958fb5f896daa5d.table.json", "ncols": 6, "nrows": 5}, "Validation Confusion Matrix Heatmap": {"_type": "image-file", "sha256": "85cb439b21eebac24434da26b084b35164b96c8857a370b780dfc1852b1e6629", "size": 63026, "path": "media/images/Validation Confusion Matrix Heatmap_6_85cb439b21eebac24434.png", "format": "png", "width": 1000, "height": 1000}, "train acc": 99.87236215112321, "train loss": 1269668.3318063056, "train vis loss": 0.37330050249706836, "train F1": 99.88834261894226, "val acc": 79.43925233644859, "val loss": 1.639341804344975, "val F1": 33.3461731672287, "_runtime": 573.2511496543884, "_step": 48, "Test F1": 48.187047243118286, "Test F1 normal": 92.42424011230469, "Test F1 AVNRT": 68.96551513671875, "Test F1 AVRT": 25.0, "Test F1 concealed": 0.0, "Test F1 EAT": 54.54545593261719, "_wandb": {"runtime": 571}}