{
    "os": "Linux-6.5.0-45-generic-x86_64-with-glibc2.35",
    "python": "3.12.2",
    "heartbeatAt": "2024-07-28T10:58:19.921283",
    "startedAt": "2024-07-28T10:58:19.325352",
    "docker": null,
    "cuda": null,
    "args": [],
    "state": "running",
    "program": "/home/tzikos/Desktop/KULeuvenThesis/hybridML.py",
    "codePathLocal": "hybridML.py",
    "codePath": "hybridML.py",
    "git": {
        "remote": "git@github.com:DimChatz/KULeuvenThesis.git",
        "commit": "fcc499bf85323c9e5b8e73a3aed579423e36457f"
    },
    "email": "dimichatzakis@gmail.com",
    "root": "/home/tzikos/Desktop/KULeuvenThesis",
    "host": "xatzospito",
    "username": "tzikos",
    "executable": "/home/tzikos/anaconda3/envs/KUThesis/bin/python",
    "cpu_count": 8,
    "cpu_count_logical": 16,
    "cpu_freq": {
        "current": 3437.9446249999996,
        "min": 400.0,
        "max": 5804.75
    },
    "cpu_freq_per_core": [
        {
            "current": 4684.368,
            "min": 400.0,
            "max": 5263.0
        },
        {
            "current": 2342.147,
            "min": 400.0,
            "max": 5743.0
        },
        {
            "current": 4682.162,
            "min": 400.0,
            "max": 5423.0
        },
        {
            "current": 1872.996,
            "min": 400.0,
            "max": 6228.0
        },
        {
            "current": 4681.583,
            "min": 400.0,
            "max": 5903.0
        },
        {
            "current": 4551.28,
            "min": 400.0,
            "max": 6228.0
        },
        {
            "current": 3326.042,
            "min": 400.0,
            "max": 5583.0
        },
        {
            "current": 4613.138,
            "min": 400.0,
            "max": 6067.0
        },
        {
            "current": 400.0,
            "min": 400.0,
            "max": 5263.0
        },
        {
            "current": 2342.025,
            "min": 400.0,
            "max": 5743.0
        },
        {
            "current": 4680.914,
            "min": 400.0,
            "max": 5423.0
        },
        {
            "current": 1873.581,
            "min": 400.0,
            "max": 6228.0
        },
        {
            "current": 4685.417,
            "min": 400.0,
            "max": 5903.0
        },
        {
            "current": 4664.655,
            "min": 400.0,
            "max": 6228.0
        },
        {
            "current": 4635.847,
            "min": 400.0,
            "max": 5583.0
        },
        {
            "current": 4671.863,
            "min": 400.0,
            "max": 6067.0
        }
    ],
    "disk": {
        "/": {
            "total": 431.4849548339844,
            "used": 307.44911193847656
        }
    },
    "gpu": "NVIDIA GeForce RTX 4060 Laptop GPU",
    "gpu_count": 1,
    "gpu_devices": [
        {
            "name": "NVIDIA GeForce RTX 4060 Laptop GPU",
            "memory_total": 8585740288
        }
    ],
    "memory": {
        "total": 14.83920669555664
    }
}
