{
    "os": "Linux-6.5.0-28-generic-x86_64-with-glibc2.35",
    "python": "3.12.2",
    "heartbeatAt": "2024-05-03T10:10:24.239142",
    "startedAt": "2024-05-03T10:10:22.920239",
    "docker": null,
    "cuda": null,
    "args": [],
    "state": "running",
    "program": "/home/tzikos/Desktop/KULeuvenThesis/main.py",
    "codePathLocal": "main.py",
    "codePath": "main.py",
    "git": {
        "remote": "git@github.com:DimChatz/KULeuvenThesis.git",
        "commit": "fa19a6e44321c29c34796e85eba85ec674d7d4e1"
    },
    "email": "dimichatzakis@gmail.com",
    "root": "/home/tzikos/Desktop/KULeuvenThesis",
    "host": "xatzospito",
    "username": "tzikos",
    "executable": "/home/tzikos/anaconda3/envs/KUThesis/bin/python",
    "cpu_count": 8,
    "cpu_count_logical": 16,
    "cpu_freq": {
        "current": 2857.1048125,
        "min": 400.0,
        "max": 5804.75
    },
    "cpu_freq_per_core": [
        {
            "current": 2337.498,
            "min": 400.0,
            "max": 5263.0
        },
        {
            "current": 400.0,
            "min": 400.0,
            "max": 5743.0
        },
        {
            "current": 2344.296,
            "min": 400.0,
            "max": 5423.0
        },
        {
            "current": 4232.609,
            "min": 400.0,
            "max": 6228.0
        },
        {
            "current": 4683.327,
            "min": 400.0,
            "max": 5903.0
        },
        {
            "current": 4621.597,
            "min": 400.0,
            "max": 6228.0
        },
        {
            "current": 4689.518,
            "min": 400.0,
            "max": 5583.0
        },
        {
            "current": 400.0,
            "min": 400.0,
            "max": 6067.0
        },
        {
            "current": 2310.219,
            "min": 400.0,
            "max": 5263.0
        },
        {
            "current": 4673.435,
            "min": 400.0,
            "max": 5743.0
        },
        {
            "current": 2447.256,
            "min": 400.0,
            "max": 5423.0
        },
        {
            "current": 2725.721,
            "min": 400.0,
            "max": 6228.0
        },
        {
            "current": 4682.037,
            "min": 400.0,
            "max": 5903.0
        },
        {
            "current": 4651.451,
            "min": 400.0,
            "max": 6228.0
        },
        {
            "current": 4690.667,
            "min": 400.0,
            "max": 5583.0
        },
        {
            "current": 1875.76,
            "min": 400.0,
            "max": 6067.0
        }
    ],
    "disk": {
        "/": {
            "total": 431.4849548339844,
            "used": 300.6921195983887
        }
    },
    "gpu": "NVIDIA GeForce RTX 4060 Laptop GPU",
    "gpu_count": 1,
    "gpu_devices": [
        {
            "name": "NVIDIA GeForce RTX 4060 Laptop GPU",
            "memory_total": 8585740288
        }
    ],
    "memory": {
        "total": 14.83919906616211
    }
}
