{"Train F1 normal": 72.03719329833984, "Val F1 normal": 74.85380554199219, "_timestamp": 1714663097.3008235, "Train F1 AVNRT": 46.09877014160156, "Val F1 AVNRT": 0.0, "Train F1 AVRT": 42.532981872558594, "Val F1 AVRT": 0.0, "Train F1 concealed": 40.20256805419922, "Val F1 concealed": 0.0, "Train F1 EAT": 23.90227699279785, "Val F1 EAT": 0.0, "Best val F1": 14.97076004743576, "Weight Name": "ECGCNNClassifier_fold4_tachy_B64_L1e-05_02-05-24-16-55", "Best Val F1 normal": 74.85380554199219, "Best Val F1 AVNRT": 0.0, "Best Val F1 AVRT": 0.0, "Best Val F1 concealed": 0.0, "Best Val F1 EAT": 0.0, "Training Confusion Matrix": {"_type": "table-file", "sha256": "32d1c76f0402175b52777f45bc0a98bdc08418baffd61fafe2545709401b7e26", "size": 374, "artifact_path": "wandb-client-artifact://nh2nhlhxdiomv11vg6wfw0674n4hh7ca007agqesbguc6yc8j7mpui8i34tsid9ig5f4w5gi814z31g7hfp1dacvoolmsj7e448x3pr3k5xse5s9nd8eondk6wpndrt1:latest/Training Confusion Matrix.table.json", "_latest_artifact_path": "wandb-client-artifact://nh2nhlhxdiomv11vg6wfw0674n4hh7ca007agqesbguc6yc8j7mpui8i34tsid9ig5f4w5gi814z31g7hfp1dacvoolmsj7e448x3pr3k5xse5s9nd8eondk6wpndrt1:latest/Training Confusion Matrix.table.json", "path": "media/table/Training Confusion Matrix_2_32d1c76f0402175b5277.table.json", "ncols": 6, "nrows": 5}, "Training Confusion Matrix Heatmap": {"_type": "image-file", "sha256": "328c67611dab6cd2063c4b09da02447b346bc6b220b3010b1fa1f833bb668a44", "size": 72901, "path": "media/images/Training Confusion Matrix Heatmap_2_328c67611dab6cd2063c.png", "format": "png", "width": 1000, "height": 1000}, "Validation Confusion Matrix": {"_type": "table-file", "sha256": "81d1189defe23a0f921c6b3bb5b7ba3e6b51dbffa6d0d87412008c16e6ed15fc", "size": 328, "artifact_path": "wandb-client-artifact://jqk3ifr01ywfmavw0otcu9tohy5zqxy144rkrtezqdr7bql01lgz2gq2ayq1n62ixl32sp6shfpxn4igtp7t3zxwxcxsh9xq0k47si6i4eco0j046b07jfmitz6qip2o:latest/Validation Confusion Matrix.table.json", "_latest_artifact_path": "wandb-client-artifact://jqk3ifr01ywfmavw0otcu9tohy5zqxy144rkrtezqdr7bql01lgz2gq2ayq1n62ixl32sp6shfpxn4igtp7t3zxwxcxsh9xq0k47si6i4eco0j046b07jfmitz6qip2o:latest/Validation Confusion Matrix.table.json", "path": "media/table/Validation Confusion Matrix_2_81d1189defe23a0f921c.table.json", "ncols": 6, "nrows": 5}, "Validation Confusion Matrix Heatmap": {"_type": "image-file", "sha256": "3acec2c612707da83cc3872c2ab165d04c1cfa4bffa133e429ad7e0ef65da509", "size": 58401, "path": "media/images/Validation Confusion Matrix Heatmap_2_3acec2c612707da83cc3.png", "format": "png", "width": 1000, "height": 1000}, "train acc": 56.644185198687566, "train loss": 1.1253157205262183, "train vis loss": 1.1253157205262183, "train F1": 44.95475888252258, "val acc": 59.813084112149525, "val loss": 1.5769660467554283, "val F1": 14.97076004743576, "_runtime": 61.934884548187256, "_step": 2, "_wandb": {"runtime": 75}}