{"Train F1 normal": 20.168067932128906, "Val F1 normal": 42.55319595336914, "_timestamp": 1715673814.0102174, "Train F1 AVNRT": 26.13065528869629, "Val F1 AVNRT": 40.000003814697266, "Train F1 AVRT": 8.196721076965332, "Val F1 AVRT": 0.0, "Train F1 concealed": 21.11111068725586, "Val F1 concealed": 28.571430206298828, "Train F1 EAT": 12.075470924377441, "Val F1 EAT": 11.7647066116333, "Best val F1": 26.951047778129578, "Weight Name": "ECGCNNClassifier_fold1_tachy_B64_L1e-06_14-05-24-09-59", "Best Val F1 normal": 0.0, "Best Val F1 AVNRT": 40.90909194946289, "Best Val F1 AVRT": 40.0, "Best Val F1 concealed": 50.0, "Best Val F1 EAT": 3.846153736114502, "Training Confusion Matrix": {"_type": "table-file", "sha256": "782d41bf93e7a4f2b9bf70242d499bf2cf1563a7964488d3c3b9da9e57f65f82", "size": 344, "artifact_path": "wandb-client-artifact://lybk2s0454xg00on118ahc069u0ydia8frg0bhx87y5ec083vcbb3uxvxyi4k1qskvot06i3w22b3x3bczlb79l2dq6yw5xlz4p97dxkkwu3nirn79fhacvsjwkuphlw:latest/Training Confusion Matrix.table.json", "_latest_artifact_path": "wandb-client-artifact://lybk2s0454xg00on118ahc069u0ydia8frg0bhx87y5ec083vcbb3uxvxyi4k1qskvot06i3w22b3x3bczlb79l2dq6yw5xlz4p97dxkkwu3nirn79fhacvsjwkuphlw:latest/Training Confusion Matrix.table.json", "path": "media/table/Training Confusion Matrix_19_782d41bf93e7a4f2b9bf.table.json", "ncols": 6, "nrows": 5}, "Training Confusion Matrix Heatmap": {"_type": "image-file", "sha256": "e28deefda111d6b95d03b0eca96068305a8eb2687c56f400cc73c6a41f499a80", "size": 68397, "path": "media/images/Training Confusion Matrix Heatmap_19_e28deefda111d6b95d03.png", "format": "png", "width": 1000, "height": 1000}, "Validation Confusion Matrix": {"_type": "table-file", "sha256": "df3408c40c4498420e981b8eea01820a8630fd75a795dfb26e35905b76850ffe", "size": 329, "artifact_path": "wandb-client-artifact://gjqjah5u780n0jk3m4gguf9ur8nkd247j500i9mcndlvhua1t7uu3e2fd6h89r7as9w7278daaq43jkwx4g2gelxevlw0wfw7rwuuq8g8i6ppzx5mh2q70tpqrm8riak:latest/Validation Confusion Matrix.table.json", "_latest_artifact_path": "wandb-client-artifact://gjqjah5u780n0jk3m4gguf9ur8nkd247j500i9mcndlvhua1t7uu3e2fd6h89r7as9w7278daaq43jkwx4g2gelxevlw0wfw7rwuuq8g8i6ppzx5mh2q70tpqrm8riak:latest/Validation Confusion Matrix.table.json", "path": "media/table/Validation Confusion Matrix_19_df3408c40c4498420e98.table.json", "ncols": 6, "nrows": 5}, "Validation Confusion Matrix Heatmap": {"_type": "image-file", "sha256": "248b9a77c23ba6a00aa5b1bcd6c2da257bc9fcb99f3d09c2af3b502d9e967564", "size": 63004, "path": "media/images/Validation Confusion Matrix Heatmap_19_248b9a77c23ba6a00aa5.png", "format": "png", "width": 1000, "height": 1000}, "train acc": 13.912009512485138, "train loss": 1.5351321354827623, "train vis loss": 1.5351321354827623, "train F1": 12.86361813545227, "val acc": 29.357798165137616, "val loss": 1.5809710463922464, "val F1": 26.809069514274597, "_runtime": 246.68496251106262, "_step": 31, "Test F1": 17.72727221250534, "Test F1 normal": 0.0, "Test F1 AVNRT": 50.0, "Test F1 AVRT": 0.0, "Test F1 concealed": 25.0, "Test F1 EAT": 13.636363983154297, "Testing Confusion Matrix": {"_type": "table-file", "sha256": "0c5c16a4da6d61c9c015eb4e20050818d284ede78ae4a848346d8b67db744f1a", "size": 329, "artifact_path": "wandb-client-artifact://iuktgaoirzpipiq0u959hx3dmpizva0bapqfv7ubfcgpdmdc89mvkpriibd8nbu7vnami2hr0x2cfirplkqa56fwpsi8wztr4r2iqxriq308w38x1qfe80blycibo1kg:latest/Testing Confusion Matrix.table.json", "_latest_artifact_path": "wandb-client-artifact://iuktgaoirzpipiq0u959hx3dmpizva0bapqfv7ubfcgpdmdc89mvkpriibd8nbu7vnami2hr0x2cfirplkqa56fwpsi8wztr4r2iqxriq308w38x1qfe80blycibo1kg:latest/Testing Confusion Matrix.table.json", "path": "media/table/Testing Confusion Matrix_31_0c5c16a4da6d61c9c015.table.json", "ncols": 6, "nrows": 5}, "Testing Confusion Matrix Heatmap": {"_type": "image-file", "sha256": "1650e68f075c55e3a09480b27558884f756fefe6662867b1e1ace103db9699eb", "size": 64336, "path": "media/images/Testing Confusion Matrix Heatmap_31_1650e68f075c55e3a094.png", "format": "png", "width": 1000, "height": 1000}, "_wandb": {"runtime": 246}}