{"Train F1 normal": 85.30901336669922, "Val F1 normal": 89.2086410522461, "_timestamp": 1719469366.157667, "Train F1 AVNRT": 61.27167510986328, "Val F1 AVNRT": 41.025638580322266, "Train F1 AVRT": 59.770118713378906, "Val F1 AVRT": 0.0, "Train F1 concealed": 59.18367385864258, "Val F1 concealed": 22.22222328186035, "Train F1 EAT": 43.820220947265625, "Val F1 EAT": 14.285715103149414, "Best val F1": 34.18382108211517, "Weight Name": "ECGCNNClassifier_fold9_tachy_B64_L1e-05_27-06-24-09-04", "Best Val F1 normal": 87.67123413085938, "Best Val F1 AVNRT": 41.025638580322266, "Best Val F1 AVRT": 0.0, "Best Val F1 concealed": 22.22222328186035, "Best Val F1 EAT": 20.0, "Training Confusion Matrix": {"_type": "table-file", "sha256": "4d307c5b048ecaf259d5f4323b92fafc3bc5918d4591e4925fbe7be6e47759e2", "size": 339, "artifact_path": "wandb-client-artifact://0vpzr37dogobmohniqlqdwc8raj8zgolsww8pbhugdyvwwqxle9nedul5egecsy4h0ss8rwar6athhnwued14iqkf6adynmfcegq6bh33xfjhamzmd063avaq5xrlr1p/Training Confusion Matrix.table.json", "_latest_artifact_path": "wandb-client-artifact://qwhhiqgqxibvh54lhayuluijauvzy8azj2utdnv5vouzwmldu1lghhps614yr3sqhq6i1fy9yoresa4tbwgo1w92jl79bxahqibdf51ntxv7jopkfhp1ti6o629sqv1f:latest/Training Confusion Matrix.table.json", "path": "media/table/Training Confusion Matrix_21_4d307c5b048ecaf259d5.table.json", "ncols": 6, "nrows": 5}, "Training Confusion Matrix Heatmap": {"_type": "image-file", "sha256": "ea89df407e367ca232db4d8bd9dab9aef79ef707ab8728b33abd7edafd586955", "size": 67853, "path": "media/images/Training Confusion Matrix Heatmap_21_ea89df407e367ca232db.png", "format": "png", "width": 1000, "height": 1000}, "Validation Confusion Matrix": {"_type": "table-file", "sha256": "49f88914de2e1f0d739c4498aebeab66f0d5075b896fdf3a299a82357e8094f7", "size": 328, "artifact_path": "wandb-client-artifact://t4so2pyukrcpf7qthqhiaxlw8e1lfha3ty7pmkx1cfg9xer7482rhoc5udxcwh6n89dmrb43uxvc6qdtrorjj2m7e31wc1b3f0espuka4h3io9wniz9bbvw8100luknf/Validation Confusion Matrix.table.json", "_latest_artifact_path": "wandb-client-artifact://vgx2kv6hcq01yc3s2x8a8vkzpyt9ysp57vxq4f627hom488p95x4fbzsloivejsedab8za6ylhva0u8wug3oaodox8prd78hvsf8p2ewl4sucumr09x9s9v54nn49oew:latest/Validation Confusion Matrix.table.json", "path": "media/table/Validation Confusion Matrix_21_49f88914de2e1f0d739c.table.json", "ncols": 6, "nrows": 5}, "Validation Confusion Matrix Heatmap": {"_type": "image-file", "sha256": "e054d3dfbc1d4b17221924f422f46bb4f5e38dc0db90f1896fb3acf0509a6dd8", "size": 61887, "path": "media/images/Validation Confusion Matrix Heatmap_21_e054d3dfbc1d4b172219.png", "format": "png", "width": 1000, "height": 1000}, "train acc": 73.23113207547169, "train loss": 13.736947851447573, "train vis loss": 0.8489806055282096, "train F1": 61.87094449996948, "val acc": 69.23076923076923, "val loss": 1.4311837881976794, "val F1": 33.34844410419464, "_runtime": 233.214684009552, "_step": 24}