{"Training Confusion Matrix": {"_type": "table-file", "sha256": "4977bb595e46839f696263cd930471513d96ff80c50518463408b8648acb571e", "size": 268, "artifact_path": "wandb-client-artifact://butpqexr3isz77w6iwo5kfrac0mm04mae973hynya6ohqguyskzu5ws5tdds4o1bea9wfyrq7975gvla1ns7l61m160ydpcf0owk4wo19snd4n87dw1ffzthrdo9t7ck/Training Confusion Matrix.table.json", "_latest_artifact_path": "wandb-client-artifact://a21dc0wdqe7iibat3u2zoside1ncz4vuayf7ud9ylr02adw69uzjevsc506yc5ui1ps7x0zwwgp1bw3swwcxu8w3mnn8h8wg4xmf7hz36vbe4hq9dtogliqb6h399d4u:latest/Training Confusion Matrix.table.json", "path": "media/table/Training Confusion Matrix_2_4977bb595e46839f6962.table.json", "ncols": 6, "nrows": 5}, "_timestamp": 1722083252.588561, "Training Confusion Matrix Heatmap": {"_type": "image-file", "sha256": "6ebebc3834d25c2f11a3981a11714cd473ae62edbc58a7cc507c3581583e92ac", "size": 53790, "path": "media/images/Training Confusion Matrix Heatmap_0_6ebebc3834d25c2f11a3.png", "format": "png", "width": 1000, "height": 1000}, "_runtime": 5.889668941497803, "_step": 3, "Validation Confusion Matrix Heatmap": {"_type": "image-file", "sha256": "38d29066b1d05216b5dc2d4dacdb8dd106796b49162ced760d935ad5cde3e188", "size": 52929, "path": "media/images/Validation Confusion Matrix Heatmap_1_38d29066b1d05216b5dc.png", "format": "png", "width": 1000, "height": 1000}, "Test Confusion Matrix Heatmap": {"_type": "image-file", "sha256": "38d29066b1d05216b5dc2d4dacdb8dd106796b49162ced760d935ad5cde3e188", "size": 52929, "path": "media/images/Test Confusion Matrix Heatmap_2_38d29066b1d05216b5dc.png", "format": "png", "width": 1000, "height": 1000}, "Training F1": 0.9885897435897437, "Validation F1": 0.9885897435897437, "Test F1": 0.9885897435897437, "_wandb": {"runtime": 13}}