{"Train F1 normal": 82.38554382324219, "Val F1 normal": 68.36363983154297, "_timestamp": 1722359659.0052452, "Train F1 AVNRT": 46.1304817199707, "Val F1 AVNRT": 26.912927627563477, "Train F1 AVRT": 98.24335479736328, "Val F1 AVRT": 96.66666412353516, "Train F1 concealed": 88.78019714355469, "Val F1 concealed": 15.094339370727539, "Train F1 EAT": 48.368690490722656, "Val F1 EAT": 8.2644624710083, "Best val F1": 49.63098466396332, "Weight Name": "ECGCNNClassifier_fold2_pre_B6_L1e-05_30-07-24-17-05", "Best Val F1 normal": 85.57875061035156, "Best Val F1 AVNRT": 16.5745849609375, "Best Val F1 AVRT": 97.52066040039062, "Best Val F1 concealed": 35.29411697387695, "Best Val F1 EAT": 13.186812400817871, "Training Confusion Matrix": {"_type": "table-file", "sha256": "221ec124f91e7c5b3b10a5ddc800822bcdc7bee69d9d65ce2b067348021cc6d8", "size": 354, "artifact_path": "wandb-client-artifact://7l88s9232n37a3qi5yfguor6ukqbwgnm2tzm6nwn3tyy79wf8jnoou3y6mz8s61846jygnsin4wj7cx9ue9i5fs5o9w9yyc0rhgiau9kmyiwpq10o970vksmbufe4eza/Training Confusion Matrix.table.json", "_latest_artifact_path": "wandb-client-artifact://doi4qu0flnd71uko5aa6e8k6ly7cqw6h3q0h5e1ey946805ukci7rpm3do4vwlzdeissoe1w8k1mv70vn12o2ab5gft6uk5zf5nledogngdivx2kq7976zdvr9x587bl:latest/Training Confusion Matrix.table.json", "path": "media/table/Training Confusion Matrix_15_221ec124f91e7c5b3b10.table.json", "ncols": 6, "nrows": 5}, "Training Confusion Matrix Heatmap": {"_type": "image-file", "sha256": "d397f05f827b76decd64f4083079b85907437a63cf58ae5f62cd6ff6786d5d87", "size": 71082, "path": "media/images/Training Confusion Matrix Heatmap_15_d397f05f827b76decd64.png", "format": "png", "width": 1000, "height": 1000}, "Validation Confusion Matrix": {"_type": "table-file", "sha256": "291a04c520b21f43c4ebcd52f01d993f80bb632f7751c92b6eee76af71bdf950", "size": 316, "artifact_path": "wandb-client-artifact://cjatn3x56h7j6s38te0g91audmbdm05on9g841uf6d3mnznqh9b4zqe94iaz2anzwh4isq0qc881wu0ujyh7mc2xqefe52z0045gulzng47gxktifv5bm16qu2hxyaut/Validation Confusion Matrix.table.json", "_latest_artifact_path": "wandb-client-artifact://x43hj3ajz9g8ilg3jiq61suxsytfkxu7o3ztltl2g2733wlhj6yh44k94cuagysk7xo657vxqebai870cnqea3v5fd3ibh2sx0w3hja5uqyfg8h30136m2ws6ypg10kp:latest/Validation Confusion Matrix.table.json", "path": "media/table/Validation Confusion Matrix_15_291a04c520b21f43c4eb.table.json", "ncols": 6, "nrows": 5}, "Validation Confusion Matrix Heatmap": {"_type": "image-file", "sha256": "aff1d3905e272b639149acaaf1061ed86cb283195b27f220591125bfd68370dc", "size": 64637, "path": "media/images/Validation Confusion Matrix Heatmap_15_aff1d3905e272b639149.png", "format": "png", "width": 1000, "height": 1000}, "train acc": 74.20738698581606, "train loss": 0.8815937878894244, "train vis loss": 0.4355293184689205, "train F1": 71.44359946250916, "val acc": 63.55140186915887, "val loss": 3.015075298634861, "val F1": 48.16661477088928, "_runtime": 7733.558153152466, "_step": 27, "Test F1": 42.21363663673401, "Test F1 normal": 86.1509017944336, "Test F1 AVNRT": 13.872833251953125, "Test F1 AVRT": 91.0714340209961, "Test F1 concealed": 7.692307949066162, "Test F1 EAT": 12.280701637268066, "Testing Confusion Matrix": {"_type": "table-file", "sha256": "314364aca509c38f77c9a7bad3cfdf00786ec1a21816efb4219ad42021f81fda", "size": 317, "artifact_path": "wandb-client-artifact://uicv6g0r4w7ntkvdy6vy4vt9958e2bdhlt3f0vfdk4zgvo2kpxhq57go7l20u9kb4ojefr49owznydmg1rkxd0xnyjm7hfn7d48i9rviv79cp47vqe90q07z2k74ckkh/Testing Confusion Matrix.table.json", "_latest_artifact_path": "wandb-client-artifact://lrx69hxnh3t102w65u7dwa8n3mz4m4ebwy4q99lpbynxd8sq4lnu17sf35lp65sp11pxcbkn613t5psb4o1vkxtzemyygl1l38j21galggnx63o4c2a6p0wp017u41jn:latest/Testing Confusion Matrix.table.json", "path": "media/table/Testing Confusion Matrix_27_314364aca509c38f77c9.table.json", "ncols": 6, "nrows": 5}, "Testing Confusion Matrix Heatmap": {"_type": "image-file", "sha256": "c4ce80da9f9af944e14253517aae50f9ab4e869c58db40eafe1f4ba697fccc48", "size": 64171, "path": "media/images/Testing Confusion Matrix Heatmap_27_c4ce80da9f9af944e142.png", "format": "png", "width": 1000, "height": 1000}, "_wandb": {"runtime": 7736}}